__main__.py
markrunner_server-0.1.6.dist-info/METADATA
markrunner_server-0.1.6.dist-info/WHEEL
markrunner_server-0.1.6.dist-info/RECORD
